{"date": "2025-12-31", "symbol": "ENTG", "reportedCurrency": "USD", "cik": "0001101302", "filingDate": "2026-02-11", "acceptedDate": "2026-02-10 18:48:26", "fiscalYear": "2025", "period": "FY", "cashAndCashEquivalents": 360400000, "shortTermInvestments": 0, "cashAndShortTermInvestments": 360400000, "netReceivables": 458700000, "accountsReceivables": 458700000, "otherReceivables": 0, "inventory": 643200, "prepaids": 0, "otherCurrentAssets": 818456800, "totalCurrentAssets": 1638200000, "propertyPlantEquipmentNet": 1744800, "goodwill": 3946700000, "intangibleAssets": 906900000, "goodwillAndIntangibleAssets": 4853600000, "longTermInvestments": 0, "taxAssets": 91600, "otherNonCurrentAssets": 1856863600, "totalNonCurrentAssets": 6712300000, "otherAssets": 0, "totalAssets": 8350500000, "totalPayables": 253900000, "accountPayables": 171500000, "otherPayables": 82400000, "accruedExpenses": 96500000, "shortTermDebt": 15800000, "capitalLeaseObligationsCurrent": 0, "taxPayables": 82400, "deferredRevenue": 49900000, "otherCurrentLiabilities": 72500000, "totalCurrentLiabilities": 488600000, "longTermDebt": 3779200000, "capitalLeaseObligationsNonCurrent": 98600000, "deferredRevenueNonCurrent": 0, "deferredTaxLiabilitiesNonCurrent": 40800000, "otherNonCurrentLiabilities": -10100000, "totalNonCurrentLiabilities": 3908500000, "otherLiabilities": 0, "capitalLeaseObligations": 98600000, "totalLiabilities": 4397100000, "treasuryStock": -7100000, "preferredStock": 0, "commonStock": 1500000, "retainedEarnings": 1558400000, "additionalPaidInCapital": 2472000000, "accumulatedOtherComprehensiveIncomeLoss": -71400000, "otherTotalStockholdersEquity": 0, "totalStockholdersEquity": 3953400000, "totalEquity": 3953400000, "minorityInterest": 0, "totalLiabilitiesAndTotalEquity": 8350500000, "totalInvestments": 0, "totalDebt": 3893600000, "netDebt": 3533200000}